pip_try/__init__.py
pip_try/demo.py
pip_try-0.1.0.dist-info/licenses/LICENSE
pip_try-0.1.0.dist-info/METADATA
pip_try-0.1.0.dist-info/WHEEL
pip_try-0.1.0.dist-info/top_level.txt
pip_try-0.1.0.dist-info/RECORD
