Metadata-Version: 2.4
Name: pip_try
Version: 0.1.0
Summary: A demo python package named pip_try
Author: lihua
License: MIT License
Project-URL: Homepage, https://example.com/pip_try
Requires-Python: >=3.8
License-File: LICENSE
Dynamic: license-file
